easy_qmainwindow.py
easy_qmainwindow-0.0.1.dist-info/METADATA
easy_qmainwindow-0.0.1.dist-info/WHEEL
easy_qmainwindow-0.0.1.dist-info/top_level.txt
easy_qmainwindow-0.0.1.dist-info/RECORD
