Metadata-Version: 2.1
Name: easy_qmainwindow
Version: 0.0.1
Summary: A simple PyQt5 wrapper for QMainWindow
Home-page: https://github.com/Locked-chess-official/easy_qmainwindow
Author: HuangHaoHua
Author-email: 13140752715@163.com
Classifier: Development Status :: 3 - Alpha
Classifier: Intended Audience :: Developers
Classifier: License :: OSI Approved :: MIT License
Classifier: Programming Language :: Python :: 3
Requires-Dist: PyQt5
